{
  "members": [
    {
      "name": "sorrycc",
      "hp": 10,
      "joined_at": 1587540411615,
      "articles": [
        2,
        1
      ]
    },
    {
      "name": "Runtu4378",
      "hp": 13,
      "articles": [],
      "joined_at": 1588952258449
    },
    {
      "name": "FeengQi",
      "hp": 13,
      "articles": [],
      "joined_at": 1588952639623
    },
    {
      "name": "ilovetochangetheworld",
      "hp": 13,
      "articles": [],
      "joined_at": 1588952639623
    },
    {
      "name": "lovemegowin",
      "hp": 13,
      "articles": [],
      "joined_at": 1588952639623
    },
    {
      "name": "pubuzhixing8",
      "hp": 13,
      "articles": [],
      "joined_at": 1588952639623
    },
    {
      "name": "ymjrcc",
      "hp": 20,
      "articles": [
        3
      ],
      "joined_at": 1588952639623
    },
    {
      "name": "Yana5417",
      "hp": 13,
      "articles": [],
      "joined_at": 1588953085814
    },
    {
      "name": "ShawDanon",
      "hp": 13,
      "articles": [],
      "joined_at": 1588953696999
    },
    {
      "name": "xiaohuoni",
      "hp": 13,
      "articles": [],
      "joined_at": 1588987287110
    },
    {
      "name": "gaowei1012",
      "hp": 13,
      "articles": [],
      "joined_at": 1588988478514
    },
    {
      "name": "Rashomon511",
      "hp": 13,
      "articles": [],
      "joined_at": 1588988478514
    },
    {
      "name": "xusanduo08",
      "hp": 13,
      "articles": [],
      "joined_at": 1588995674653
    },
    {
      "name": "AspirinMrmi",
      "hp": 14,
      "articles": [],
      "joined_at": 1589104970304
    },
    {
      "name": "soolx",
      "hp": 14,
      "articles": [],
      "joined_at": 1589104970304
    },
    {
      "name": "xiaoxiangmoe",
      "hp": 14,
      "articles": [],
      "joined_at": 1589104970304
    },
    {
      "name": "shusheng-github",
      "hp": 14,
      "articles": [],
      "joined_at": 1589105517004
    },
    {
      "name": "YAN7",
      "hp": 14,
      "articles": [],
      "joined_at": 1589105517004
    },
    {
      "name": "alexPang6",
      "hp": 14,
      "articles": [],
      "joined_at": 1589106113882
    },
    {
      "name": "LukerSpringtree",
      "hp": 14,
      "articles": [],
      "joined_at": 1589108840838
    },
    {
      "name": "QC-L",
      "hp": 14,
      "articles": [],
      "joined_at": 1589108840838
    },
    {
      "name": "chuangwei",
      "hp": 14,
      "articles": [],
      "joined_at": 1589113289440
    },
    {
      "name": "forl",
      "hp": 14,
      "articles": [],
      "joined_at": 1589113289440
    },
    {
      "name": "undefined-lee",
      "hp": 14,
      "articles": [],
      "joined_at": 1589113289440
    },
    {
      "name": "zpd106",
      "hp": 14,
      "articles": [],
      "joined_at": 1589113900774
    },
    {
      "name": "3crazyspecial",
      "hp": 14,
      "articles": [],
      "joined_at": 1589114506739
    },
    {
      "name": "hkc452",
      "hp": 14,
      "articles": [],
      "joined_at": 1589114506739
    },
    {
      "name": "leonway",
      "hp": 14,
      "articles": [],
      "joined_at": 1589114506739
    },
    {
      "name": "soarL",
      "hp": 14,
      "articles": [],
      "joined_at": 1589114506739
    },
    {
      "name": "wstreet",
      "hp": 14,
      "articles": [],
      "joined_at": 1589114506739
    },
    {
      "name": "dxc111",
      "hp": 14,
      "articles": [],
      "joined_at": 1589115109482
    },
    {
      "name": "godzzh",
      "hp": 14,
      "articles": [],
      "joined_at": 1589115109482
    },
    {
      "name": "guimeisang",
      "hp": 14,
      "articles": [],
      "joined_at": 1589115109482
    },
    {
      "name": "icodytan",
      "hp": 14,
      "articles": [],
      "joined_at": 1589115109482
    },
    {
      "name": "forever-chen",
      "hp": 14,
      "articles": [],
      "joined_at": 1589115720385
    },
    {
      "name": "hqylss111",
      "hp": 14,
      "articles": [],
      "joined_at": 1589115720385
    },
    {
      "name": "MasonTao",
      "hp": 14,
      "articles": [],
      "joined_at": 1589115720385
    },
    {
      "name": "SawWu",
      "hp": 14,
      "articles": [],
      "joined_at": 1589115720385
    },
    {
      "name": "tunoon",
      "hp": 14,
      "articles": [],
      "joined_at": 1589115720385
    },
    {
      "name": "WanderHuang",
      "hp": 14,
      "articles": [],
      "joined_at": 1589115720385
    },
    {
      "name": "weiqinke",
      "hp": 14,
      "articles": [],
      "joined_at": 1589115720385
    }
  ]
}